CHANGELOG.md
LICENSE.Apache.v2
LICENSE.GPL.v2
MANIFEST.in
README.license.md
README.rst
VERSION
setup.cfg
setup.py
pr2modules/__init__.py
pr2modules/nslink/__init__.py
pr2modules/nslink/nslink.py
pr2modules/nslink/process/__init__.py
pr2modules/nslink/process/proxy.py
pr2modules/remote/__init__.py
pr2modules/remote/__main__.py
pr2modules/remote/shell.py
pyroute2.nslink.egg-info/PKG-INFO
pyroute2.nslink.egg-info/SOURCES.txt
pyroute2.nslink.egg-info/dependency_links.txt
pyroute2.nslink.egg-info/entry_points.txt
pyroute2.nslink.egg-info/namespace_packages.txt
pyroute2.nslink.egg-info/requires.txt
pyroute2.nslink.egg-info/top_level.txt